authware/__init__.py
authware/application.py
authware/cryptography.py
authware/exceptions.py
authware/hwid.py
authware/user.py
authware/utils.py
authware/win_hwid.py
authware-2.0.1.dist-info/METADATA
authware-2.0.1.dist-info/WHEEL
authware-2.0.1.dist-info/licenses/LICENSE
authware-2.0.1.dist-info/RECORD
