Metadata-Version: 2.1
Name: authware
Version: 2.0.1
Summary: Sync & async wrapper/SDK for the Authware API in Python 3.5+
Project-URL: Homepage, https://authware.org
Project-URL: Bug Tracker, https://github.com/AuthwareCloud/python-sdk/issues
Author-email: Authware <support@authware.org>
License-File: LICENSE
Classifier: License :: OSI Approved :: MIT License
Classifier: Operating System :: OS Independent
Classifier: Programming Language :: Python :: 3
Requires-Python: >=3.5
